block_types/__init__.py
block_types/_nbdev.py
block_types/blocks/__init__.py
block_types/blocks/blocks.py
block_types/blocks/preprocessing.py
block_types/config/__init__.py
block_types/config/bt_defaults.py
block_types/core/__init__.py
block_types/core/block_types.py
block_types/core/compose.py
block_types/core/data_conversion.py
block_types/core/utils.py
block_types/datasets/__init__.py
block_types/datasets/datasets.py
block_types/utils/__init__.py
block_types/utils/dummies.py
block_types/utils/nbdev_utils.py
block_types/utils/utils.py
block_types-0.0.5.dist-info/LICENSE
block_types-0.0.5.dist-info/METADATA
block_types-0.0.5.dist-info/WHEEL
block_types-0.0.5.dist-info/entry_points.txt
block_types-0.0.5.dist-info/top_level.txt
block_types-0.0.5.dist-info/RECORD
