Metadata-Version: 2.1
Name: block-types
Version: 0.0.5
Summary: Write highly modular, compact, and decoupled data science pipelines.
Home-page: https://github.com/Jaume-JCI/block-types/tree/main/
Author: Jaume Amores
Author-email: jamorej@jci.com
License: MIT License
Keywords: Block Types
Platform: UNKNOWN
Classifier: Development Status :: 3 - Alpha
Classifier: Intended Audience :: Developers
Classifier: Natural Language :: English
Classifier: Programming Language :: Python :: 3.7
Classifier: Programming Language :: Python :: 3.8
Classifier: License :: OSI Approved :: MIT License
Requires-Python: >=3.7
Requires-Dist: pandas
Requires-Dist: scikit-learn
Requires-Dist: pyarrow
Requires-Dist: numpy
Requires-Dist: nbdev
Requires-Dist: pytest
Requires-Dist: ipython
Requires-Dist: jupyter
Requires-Dist: ipykernel
Requires-Dist: matplotlib
Requires-Dist: graphviz
